mensaje/__init__.py
mensaje/adios/__init__.py
mensaje/adios/despedidas.py
mensaje/hola/__init__.py
mensaje/hola/saludos.py
test/__init__.py
test/test_hola.py
Mensajes_Eclavo-5.0.dist-info/LICENSE
Mensajes_Eclavo-5.0.dist-info/METADATA
Mensajes_Eclavo-5.0.dist-info/WHEEL
Mensajes_Eclavo-5.0.dist-info/top_level.txt
Mensajes_Eclavo-5.0.dist-info/RECORD
