Metadata-Version: 2.1
Name: Mensajes-Eclavo
Version: 5.0
Summary: un paquete para saludar y despedir
Home-page: https://www.xepi.dev
Author: Eddynson Clavo Chumpitaz
Author-email: edyclavo@hotmail.com
Classifier: Environment :: Console
Classifier: Environment :: Console :: Curses
Classifier: Environment :: Console :: Framebuffer
Classifier: Environment :: Console :: Newt
Classifier: Environment :: Console :: svgalib
Classifier: Environment :: GPU
Classifier: Environment :: GPU :: NVIDIA CUDA
Classifier: Environment :: GPU :: NVIDIA CUDA :: 1.0
Classifier: Environment :: GPU :: NVIDIA CUDA :: 1.1
License-File: LICENSE
Requires-Dist: numpy >=1.23.0
